libreppc/__init__.py
libreppc/__main__.py
libreppc/constants.py
libreppc/libreppc.py
libreppc/static/bloger.css
libreppc/static/mastodon.css
libreppc/templates/index.html
libreppc/templates/post.html
libreppc-0.2.1.1.dist-info/LICENSE
libreppc-0.2.1.1.dist-info/METADATA
libreppc-0.2.1.1.dist-info/WHEEL
libreppc-0.2.1.1.dist-info/top_level.txt
libreppc-0.2.1.1.dist-info/RECORD
