Metadata-Version: 2.1
Name: libreppc
Version: 0.2.1.1
Summary: A simple profile page creator.
Home-page: https://codeberg.org/librehub/libreppc
Author: loliconshik3
Author-email: loliconshik3@gmail.com
Keywords: python,profile,html,css,markdown,profile page,page,site,personal page
Classifier: Development Status :: 1 - Planning
Classifier: Intended Audience :: Developers
Classifier: Programming Language :: Python :: 3
Classifier: Operating System :: Unix
Classifier: Operating System :: MacOS :: MacOS X
Classifier: Operating System :: Microsoft :: Windows
License-File: LICENSE
Requires-Dist: flask
Requires-Dist: markdown
Requires-Dist: feedgen
Requires-Dist: pytz
Requires-Dist: pygments
